tls_requests/__init__.py
tls_requests-0.0.2.dist-info/METADATA
tls_requests-0.0.2.dist-info/WHEEL
tls_requests-0.0.2.dist-info/top_level.txt
tls_requests-0.0.2.dist-info/RECORD
