Metadata-Version: 2.1
Name: tls-requests
Version: 0.0.2
Summary: A package
Author: Me
Author-email: totally@my.mail
Keywords: python
Classifier: Development Status :: 1 - Planning
Classifier: Intended Audience :: Developers
Classifier: Programming Language :: Python :: 3
Classifier: Operating System :: Unix
Classifier: Operating System :: MacOS :: MacOS X
Classifier: Operating System :: Microsoft :: Windows
Requires-Dist: dn
